demodapk/__init__.py
demodapk/__main__.py
demodapk/baseconf.py
demodapk/cli.py
demodapk/hex.py
demodapk/mark.py
demodapk/misc.py
demodapk/mods.py
demodapk/patch.py
demodapk/py.typed
demodapk/schema.json
demodapk/schema.py
demodapk/tool.py
demodapk/utils.py
demodapk-1.1.17.dist-info/entry_points.txt
demodapk-1.1.17.dist-info/licenses/LICENSE.txt
demodapk-1.1.17.dist-info/WHEEL
demodapk-1.1.17.dist-info/METADATA
demodapk-1.1.17.dist-info/RECORD
