Metadata-Version: 2.4
Name: demodapk
Version: 1.1.17
Summary: A Demo CLI for modifying APK resources via config
Keywords: arsc,apk,apkeditor,demo
Author-email: Veha0001 <84841152+Veha0001@users.noreply.github.com>
Maintainer-email: Veha0001 <84841152+Veha0001@users.noreply.github.com>
Requires-Python: >=3.10
License-Expression: GPL-3.0-or-later
License-File: LICENSE.txt
Requires-Dist: art
Requires-Dist: auto-click-auto
Requires-Dist: rich
Requires-Dist: rich-click
Requires-Dist: rich-gradient
Requires-Dist: inquirer
Requires-Dist: mkdocs ; extra == "dev"
Requires-Dist: mkdocs-material ; extra == "dev"
Requires-Dist: mkdocs-github-admonitions-plugin ; extra == "dev"
Project-URL: Documentation, https://demodapk.netlify.app
Project-URL: Homepage, https://github.com/Veha0001/DemodAPK
Project-URL: Issues, https://github.com/Veha0001/DemodAPK/issues
Project-URL: Repository, https://github.com/Veha0001/DemodAPK
Provides-Extra: dev
